blueskyapi/__init__.py
blueskyapi/__version__.py
blueskyapi/client.py
blueskyapi/default_config.py
blueskyapi/errors.py
blueskyapi-0.2.0.dist-info/LICENSE
blueskyapi-0.2.0.dist-info/METADATA
blueskyapi-0.2.0.dist-info/WHEEL
blueskyapi-0.2.0.dist-info/RECORD
