Metadata-Version: 2.1
Name: blueskyapi
Version: 0.2.0
Summary: Client for blueskyapi.io
Home-page: https://blueskyapi.io
License: MIT
Keywords: weather,data,api
Author: blueskyapi.io
Author-email: contact@blueskyapi.io
Requires-Python: >=3.7.1,<4.0.0
Classifier: License :: OSI Approved :: MIT License
Classifier: Programming Language :: Python :: 3
Classifier: Programming Language :: Python :: 3.8
Classifier: Programming Language :: Python :: 3.9
Classifier: Programming Language :: Python :: 3.10
Classifier: Programming Language :: Python :: 3.11
Requires-Dist: pandas (>=1.1,<2.0)
Requires-Dist: requests (>=2.0,<3.0)
Project-URL: Documentation, https://blueskyapi.readthedocs.io/en/stable/
Project-URL: Repository, https://github.com/bluesky-api/python-client
